dev/__init__.py
dev/code.py
dev/duration.py
dev/stht.py
dev/t.py
dev/timepicker.py
fletmint/__init__.py
fletmint/audioplayer.py
fletmint/badge.py
fletmint/button.py
fletmint/carousel.py
fletmint/checkbox.py
fletmint/code.py
fletmint/color_picker.py
fletmint/datepicker.py
fletmint/dropdown.py
fletmint/profile.py
fletmint/radio.py
fletmint/slider.py
fletmint/stepper.py
fletmint/tab_switch.py
fletmint/table.py
fletmint/tags_input.py
fletmint/text_input.py
fletmint/toast.py
fletmint/toggle.py
fletmint/toggle_switch.py
fletmint/videoplayer.py
fletmint/utils/__init__.py
fletmint/utils/change_icon.py
fletmint-0.1.6.2.dist-info/METADATA
fletmint-0.1.6.2.dist-info/WHEEL
fletmint-0.1.6.2.dist-info/top_level.txt
fletmint-0.1.6.2.dist-info/RECORD
