Metadata-Version: 2.1
Name: fletmint
Version: 0.1.6.2
Summary: A sharp and modern components library for Flet
Author: Edoardo Balducci
Author-email: edoardoba2004@gmail.com
Project-URL: support, https://www.patreon.com/edoardobalducci
Project-URL: repository, https://github.com/Bbalduzz/fletmint
Project-URL: tracker, https://github.com/Bbalduzz/fletmint/issues
Classifier: Development Status :: 3 - Alpha
Classifier: Intended Audience :: Developers
Classifier: License :: OSI Approved :: MIT License
Classifier: Programming Language :: Python :: 3.8
Classifier: Programming Language :: Python :: 3.9
Classifier: Programming Language :: Python :: 3.10
Classifier: Programming Language :: Python :: 3.11
Classifier: Programming Language :: Python :: 3.12
Requires-Python: >=3.8
Requires-Dist: flet
